SpotDown/__init__.py
SpotDown/main.py
SpotDown/downloader/__init__.py
SpotDown/downloader/batch_downloader.py
SpotDown/downloader/youtube_downloader.py
SpotDown/extractor/__init__.py
SpotDown/extractor/spotify_extractor.py
SpotDown/extractor/youtube_extractor.py
SpotDown/upload/version.py
SpotDown/utils/__init__.py
SpotDown/utils/config_json.py
SpotDown/utils/console_utils.py
SpotDown/utils/ffmpeg_installer.py
SpotDown/utils/headers.py
SpotDown/utils/logger.py
SpotDown/utils/os.py
spotdown-1.5.0.dist-info/licenses/LICENSE
spotdown-1.5.0.dist-info/METADATA
spotdown-1.5.0.dist-info/WHEEL
spotdown-1.5.0.dist-info/entry_points.txt
spotdown-1.5.0.dist-info/top_level.txt
spotdown-1.5.0.dist-info/RECORD
