Metadata-Version: 2.4
Name: SpotDown
Version: 1.5.0
Summary: A command-line program to download music
Home-page: https://github.com/Arrowar/spotdown
Author: Arrowar
Author-email: author@example.com
Classifier: Programming Language :: Python :: 3
Classifier: License :: OSI Approved :: GNU General Public License v3 (GPLv3)
Classifier: Operating System :: OS Independent
Requires-Python: >=3.8
License-File: LICENSE
Requires-Dist: rich
Requires-Dist: httpx
Requires-Dist: unidecode
Requires-Dist: ua-generator
Requires-Dist: yt-dlp
Requires-Dist: spotipy
Dynamic: author
Dynamic: author-email
Dynamic: classifier
Dynamic: description
Dynamic: description-content-type
Dynamic: home-page
Dynamic: license-file
Dynamic: requires-dist
Dynamic: requires-python
Dynamic: summary
